robotframework_rp_tools/__init__.py
robotframework_rp_tools/listener.py
robotframework_rp_tools/listener_model.py
robotframework_rp_tools/service.py
robotframework_rp_tools/variables.py
robotframework_rp_tools/visitor.py
robotframework_rp_tools/visitor_model.py
robotframework_rp_tools-0.0.6.dist-info/LICENSE.txt
robotframework_rp_tools-0.0.6.dist-info/METADATA
robotframework_rp_tools-0.0.6.dist-info/WHEEL
robotframework_rp_tools-0.0.6.dist-info/top_level.txt
robotframework_rp_tools-0.0.6.dist-info/RECORD
