Metadata-Version: 2.1
Name: robotframework-rp-tools
Version: 0.0.6
Summary: Listener and visitor modules for integration with ReportPortal
Home-page: https://github.com/Shumodan/robotframework_tools
Author: Alexander Evdokimov
Author-email: 1812gg@gmail.com
License: UNKNOWN
Platform: UNKNOWN
Classifier: Programming Language :: Python :: 3
Classifier: Topic :: Software Development :: Testing
Classifier: License :: OSI Approved :: MIT License
Classifier: Operating System :: OS Independent
Classifier: Framework :: Robot Framework
Classifier: Framework :: Robot Framework :: Library
Classifier: Framework :: Robot Framework :: Tool
Requires-Python: >=3.7
Requires-Dist: robotframework
Requires-Dist: reportportal-client
